spxquery/__init__.py
spxquery/core/__init__.py
spxquery/core/config.py
spxquery/core/download.py
spxquery/core/pipeline.py
spxquery/core/query.py
spxquery/processing/__init__.py
spxquery/processing/background.py
spxquery/processing/fits_handler.py
spxquery/processing/lightcurve.py
spxquery/processing/magnitudes.py
spxquery/processing/photometry.py
spxquery/utils/__init__.py
spxquery/utils/helpers.py
spxquery/utils/params.py
spxquery/utils/spherex_mef.py
spxquery/visualization/__init__.py
spxquery/visualization/plots.py
spxquery-0.2.2.dist-info/METADATA
spxquery-0.2.2.dist-info/WHEEL
spxquery-0.2.2.dist-info/entry_points.txt
spxquery-0.2.2.dist-info/licenses/LICENSE
spxquery-0.2.2.dist-info/RECORD
