Metadata-Version: 2.4
Name: spxquery
Version: 0.2.2
Summary: SPHEREx time-domain analysis package for querying and analyzing spectral image data
License-Expression: MIT
License-File: LICENSE
Keywords: astronomy,spherex,spectroscopy,time-domain,photometry,astrophysics
Author: Wenke Ren
Author-email: wenkeren.astro@gmail.com
Maintainer: Wenke Ren
Maintainer-email: wenkeren.astro@gmail.com
Requires-Python: >=3.11
Classifier: Development Status :: 4 - Beta
Classifier: Intended Audience :: Science/Research
Classifier: Topic :: Scientific/Engineering :: Astronomy
Classifier: Programming Language :: Python :: 3
Classifier: Programming Language :: Python :: 3.11
Classifier: Programming Language :: Python :: 3.12
Classifier: Programming Language :: Python :: 3.13
Classifier: Operating System :: OS Independent
Requires-Dist: astropy (>=7.0,<8.0)
Requires-Dist: matplotlib (>=3.9,<4.0)
Requires-Dist: numpy (>=1.26.0,<3.0.0)
Requires-Dist: pandas (>=2.0,<3.0)
Requires-Dist: photutils (>=2.3.0,<3.0.0)
Requires-Dist: pyvo (>=1.6,<2.0)
Requires-Dist: pyyaml (>=6.0.3,<7.0.0)
Requires-Dist: scipy (>=1.12,<2.0)
Requires-Dist: tqdm (>=4.64,<5.0)
Project-URL: Documentation, https://spxquery.readthedocs.io
Project-URL: Homepage, https://github.com/WenkeRen/spxquery
Project-URL: Issues, https://github.com/WenkeRen/spxquery/issues
Project-URL: Repository, https://github.com/WenkeRen/spxquery
